[
    {
        "source": "經濟日報",
        "title": "AI類股持續走弱和油價勁揚 美股收黑",
        "url": "https://money.udn.com/money/story/123398/9635383",
        "time": "焦點頭條"
    },
    {
        "source": "經濟日報",
        "title": "AI類股持續走弱和油價勁揚 美股收黑",
        "url": "https://money.udn.com/money/story/123398/9635383?from=edn_maintab_index",
        "time": "焦點頭條"
    },
    {
        "source": "經濟日報",
        "title": "大盤崩跌2,953點 史上最慘 外資狂砍1,883億元 八大公股進場護盤",
        "url": "https://money.udn.com/money/story/5607/9635190?from=edn_maintab_index",
        "time": "焦點頭條"
    },
    {
        "source": "經濟日報",
        "title": "慶連續 7 年信任度第一／訂經濟每日不到 5 元，再抽 101 景觀 Buffet",
        "url": "https://money.udn.com/money/story/123882/9603372?from=edn_maintab_index_mkt2607",
        "time": "焦點頭條"
    },
    {
        "source": "經濟日報",
        "title": "全球晶片類股 湧現賣壓 分析師點出股價偏高、資金輪動等三原因",
        "url": "https://money.udn.com/money/story/5599/9635195?from=edn_maintab_index",
        "time": "焦點頭條"
    },
    {
        "source": "經濟日報",
        "title": "台股短線面臨兩大考驗 四大投顧展望下周盤勢 提防整理期拉長",
        "url": "https://money.udn.com/money/story/5607/9635191?from=edn_maintab_index",
        "time": "焦點頭條"
    },
    {
        "source": "經濟日報",
        "title": "台積目標價 逆勢掀調升潮 大摩喊拉回就買",
        "url": "https://money.udn.com/money/story/5607/9635207?from=edn_maintab_index",
        "time": "焦點頭條"
    },
    {
        "source": "經濟日報",
        "title": "金管會座談聚焦協助金融監理 銀行獨董賦能 強化調查權",
        "url": "https://money.udn.com/money/story/5613/9635154?from=edn_maintab_index",
        "time": "焦點頭條"
    },
    {
        "source": "經濟日報",
        "title": "青安3.0總價門檻 北市僅75%合格 未來每四件住宅交易 恐就有一件價格超標",
        "url": "https://money.udn.com/money/story/5621/9635149?from=edn_maintab_index",
        "time": "焦點頭條"
    },
    {
        "source": "經濟日報",
        "title": "中聯致癌油回收率僅三成 卓揆致歉 要求檢調嚴查嚴辦",
        "url": "https://money.udn.com/money/story/7307/9635160?from=edn_maintab_index",
        "time": "焦點頭條"
    },
    {
        "source": "經濟日報",
        "title": "Google最強AI模型 延遲亮相 Gemini 3.5 Pro落後預定時程數個月",
        "url": "https://money.udn.com/money/story/5599/9635172?from=edn_maintab_index",
        "time": "焦點頭條"
    },
    {
        "source": "經濟日報",
        "title": "市場憂美伊衝突加劇　油價勁揚",
        "url": "https://money.udn.com/money/story/5599/9635395?from=edn_newest_index",
        "time": "焦點頭條"
    },
    {
        "source": "經濟日報",
        "title": "全球高溫紀錄常出現在聖嬰年？ 專家曝有3個可能原因",
        "url": "https://money.udn.com/money/story/122328/9635392?from=edn_newest_index",
        "time": "焦點頭條"
    },
    {
        "source": "經濟日報",
        "title": "今熱飆37度高溫防午後大雷雨 吳德榮：下周有多個熱帶擾動醞釀發展",
        "url": "https://money.udn.com/money/story/122328/9635389?from=edn_newest_index",
        "time": "焦點頭條"
    },
    {
        "source": "經濟日報",
        "title": "清晨4時9分花蓮近海規模4.1地震 最大震度2級 6縣市有感",
        "url": "https://money.udn.com/money/story/122328/9635387?from=edn_newest_index",
        "time": "焦點頭條"
    },
    {
        "source": "經濟日報",
        "title": "AI類股持續走弱和油價勁揚 美股收黑",
        "url": "https://money.udn.com/money/story/123398/9635383?from=edn_newest_index",
        "time": "焦點頭條"
    },
    {
        "source": "經濟日報",
        "title": "川普賣「早幾毫秒看到他貼文」！美總統一言撼市場 交易商付費搶先機",
        "url": "https://money.udn.com/money/story/5599/9633303?from=edn_hottest_index",
        "time": "焦點頭條"
    },
    {
        "source": "經濟日報",
        "title": "基辛格：英特爾讓商務人士掌權後走上岔路 陸圍台衝擊遠超大蕭條",
        "url": "https://money.udn.com/money/story/5599/9634702?from=edn_hottest_index",
        "time": "焦點頭條"
    },
    {
        "source": "經濟日報",
        "title": "美股早盤／陸 AI 新模型震撼全球 四大指數重挫 費半崩5%陷熊市",
        "url": "https://money.udn.com/money/story/123398/9635030?from=edn_hottest_index",
        "time": "焦點頭條"
    },
    {
        "source": "經濟日報",
        "title": "台股重挫為史上最大單日跌點 金管會回應了",
        "url": "https://money.udn.com/money/story/5613/9634865?from=edn_hottest_index",
        "time": "焦點頭條"
    },
    {
        "source": "經濟日報",
        "title": "大股東減持傳聞不斷 國巨發聲明了",
        "url": "https://money.udn.com/money/story/5612/9634614?from=edn_hottest_index",
        "time": "焦點頭條"
    },
    {
        "source": "經濟日報",
        "title": "輝達也不敢忽視！台灣量子產業鏈全解析",
        "url": "https://money.udn.com/money/story/124478/9585782?from=edn_subtab_index",
        "time": "焦點頭條"
    },
    {
        "source": "經濟日報",
        "title": "夏季房市關鍵報告1／25年最狂交屋潮來了！ 為何專家說建商沒壓力、房價反而可能上揚",
        "url": "https://money.udn.com/money/story/124480/9626371?from=edn_subtab_index",
        "time": "焦點頭條"
    },
    {
        "source": "經濟日報",
        "title": "Q3總經報告1／通膨催促美國升息 恐加速在台外資出走 台美經濟都傷？",
        "url": "https://money.udn.com/money/story/124480/9623832?from=edn_subtab_index",
        "time": "焦點頭條"
    },
    {
        "source": "經濟日報",
        "title": "AI世代理財1／新世代重寫致富路徑 買股、開槓桿買台積電成青年理財新日常",
        "url": "https://money.udn.com/money/story/124480/9618031?from=edn_subtab_index",
        "time": "焦點頭條"
    },
    {
        "source": "經濟日報",
        "title": "補貼競賽下的台灣選擇",
        "url": "https://money.udn.com/money/story/5629/9632925?from=edn_course_index",
        "time": "焦點頭條"
    },
    {
        "source": "經濟日報",
        "title": "搭橋：AI 真正的殺手級應用",
        "url": "https://money.udn.com/money/story/5629/9630394?from=edn_course_index",
        "time": "焦點頭條"
    },
    {
        "source": "經濟日報",
        "title": "股市瘋槓桿 撼動金融穩定",
        "url": "https://money.udn.com/money/story/5629/9627892?from=edn_course_index",
        "time": "焦點頭條"
    },
    {
        "source": "經濟日報",
        "title": "台積漲價背後的定價權賽局",
        "url": "https://money.udn.com/money/story/5629/9625563?from=edn_course_index",
        "time": "焦點頭條"
    },
    {
        "source": "經濟日報",
        "title": "注意股制度改革的關鍵思考",
        "url": "https://money.udn.com/money/story/5629/9623186?from=edn_course_index",
        "time": "焦點頭條"
    },
    {
        "source": "經濟日報",
        "title": "AI重塑文化內容產業鏈",
        "url": "https://money.udn.com/money/story/5629/9618788?from=edn_course_index",
        "time": "焦點頭條"
    },
    {
        "source": "經濟日報",
        "title": "法人買盤先進場 鎖定10檔財報亮麗股",
        "url": "https://money.udn.com/money/story/5607/9634860?from=edn_VIP_index_side",
        "time": "焦點頭條"
    },
    {
        "source": "經濟日報",
        "title": "職場霸凌新法上路！主管別再說「以前都這樣管」如何要求績效又不踩紅線？",
        "url": "https://money.udn.com/money/story/5648/9634985?from=edn_VIP_index_side",
        "time": "焦點頭條"
    },
    {
        "source": "經濟日報",
        "title": "AI-RAN時代來了 哪些台廠擠進前段班？",
        "url": "https://money.udn.com/money/story/5612/9634812?from=edn_VIP_index_side",
        "time": "焦點頭條"
    },
    {
        "source": "經濟日報",
        "title": "美國商品期貨交易委員會調查白宮提詞器操作員 涉川普演講押注獲利",
        "url": "https://money.udn.com/money/story/5599/9633449?from=edn_bloomberg_index_side",
        "time": "焦點頭條"
    },
    {
        "source": "經濟日報",
        "title": "新易盛據悉提交融資不超過50億美元的香港上市申請",
        "url": "https://money.udn.com/money/story/5604/9634251?from=edn_bloomberg_index_side",
        "time": "焦點頭條"
    },
    {
        "source": "經濟日報",
        "title": "中聯致癌油回收率僅三成 卓揆致歉 要求檢調嚴查嚴辦",
        "url": "https://money.udn.com/money/story/7307/9635160?from=edn_focus_index",
        "time": "焦點頭條"
    },
    {
        "source": "經濟日報",
        "title": "新應材斥資45億元擴產能 本土半導體鏈自主化再邁大步",
        "url": "https://money.udn.com/money/story/5612/9635175?from=edn_industry_index",
        "time": "焦點頭條"
    },
    {
        "source": "經濟日報",
        "title": "黑色星期五 台股大殺盤 15強棒 勇守「生命線」",
        "url": "https://money.udn.com/money/story/5607/9635205?from=edn_stock_index",
        "time": "焦點頭條"
    },
    {
        "source": "經濟日報",
        "title": "AI類股持續走弱和油價勁揚 美股收黑",
        "url": "https://money.udn.com/money/story/123398/9635383?from=edn_world_index",
        "time": "焦點頭條"
    },
    {
        "source": "經濟日報",
        "title": "世界人工智能大會／ 習近平喊 AI 賦能 暗批美國",
        "url": "https://money.udn.com/money/story/5603/9635210?from=edn_china_index",
        "time": "焦點頭條"
    },
    {
        "source": "經濟日報",
        "title": "金管會座談聚焦協助金融監理 銀行獨董賦能 強化調查權",
        "url": "https://money.udn.com/money/story/5613/9635154?from=edn_finance_index",
        "time": "焦點頭條"
    },
    {
        "source": "經濟日報",
        "title": "7月17日 期交所夜盤行情",
        "url": "https://money.udn.com/money/story/11112/9635379?from=edn_futures_index",
        "time": "焦點頭條"
    },
    {
        "source": "經濟日報",
        "title": "00692、00900等五檔台股 ETF 換股！成分股名單一次看",
        "url": "https://money.udn.com/money/story/5618/9634648?from=edn_finmanagement_index",
        "time": "焦點頭條"
    },
    {
        "source": "經濟日報",
        "title": "青安3.0總價門檻 北市僅75%合格 未來每四件住宅交易 恐就有一件價格超標",
        "url": "https://money.udn.com/money/story/5621/9635149?from=edn_house_index",
        "time": "焦點頭條"
    },
    {
        "source": "經濟日報",
        "title": "整理包／青安3.0拍板8月上路！四大新制、四大門檻 婚育加碼等重點一次看",
        "url": "https://money.udn.com/money/story/124512/9632009",
        "time": "焦點頭條"
    },
    {
        "source": "經濟日報",
        "title": "嘉義私藏景點曝光！開車15分鐘直達仁義潭 造訪「台版神隱少女湯屋」清豐濤月、湖景窯烤披薩與人氣私宅咖啡",
        "url": "https://money.udn.com/money/story/123060/9631334?from=edn_life_index",
        "time": "焦點頭條"
    },
    {
        "source": "經濟日報",
        "title": "名人書房／新光人壽業務通路總處執行長劉信成 轉動「10倍成長思維」",
        "url": "https://money.udn.com/money/story/122332/9632864?from=edn_off_index",
        "time": "焦點頭條"
    }
]